{
  "id": "practical-magic",
  "name": "kingdomFeats.practical-magic.name",
  "level": 1,
  "requirements": {
    "skillRanks": {
      "magic": 1
    }
  },
  "text": "kingdomFeats.practical-magic.text",
  "modifiers": [
    {
      "name": "Practical Magic",
      "buttonLabel": "+1 Circumstance to Magic",
      "type": "circumstance",
      "applyIf": [
        {
          "eq": [
            "@skill",
            "magic"
          ]
        }
      ],
      "enabled": true,
      "value": 1
    }
  ],
  "increaseUsableSkills": {
    "engineering": [
      "magic"
    ]
  }
}